MavenRumenjiaochengCYuyanBianchengWang/README.md
MavenRumenjiaochengCYuyanBianchengWang/__init__.py
MavenRumenjiaochengCYuyanBianchengWang/__main__.py
MavenRumenjiaochengCYuyanBianchengWang/file.epub
MavenRumenjiaochengCYuyanBianchengWang/index.html
MavenRumenjiaochengCYuyanBianchengWang/css/__init__.py
MavenRumenjiaochengCYuyanBianchengWang/css/annotations.css
MavenRumenjiaochengCYuyanBianchengWang/css/main.css
MavenRumenjiaochengCYuyanBianchengWang/css/normalize.css
MavenRumenjiaochengCYuyanBianchengWang/css/popup.css
MavenRumenjiaochengCYuyanBianchengWang/font/__init__.py
MavenRumenjiaochengCYuyanBianchengWang/font/fontello.eot
MavenRumenjiaochengCYuyanBianchengWang/font/fontello.svg
MavenRumenjiaochengCYuyanBianchengWang/font/fontello.ttf
MavenRumenjiaochengCYuyanBianchengWang/font/fontello.woff
MavenRumenjiaochengCYuyanBianchengWang/img/__init__.py
MavenRumenjiaochengCYuyanBianchengWang/img/annotator-glyph-sprite.png
MavenRumenjiaochengCYuyanBianchengWang/img/annotator-icon-sprite.png
MavenRumenjiaochengCYuyanBianchengWang/img/apple-touch-icon.png
MavenRumenjiaochengCYuyanBianchengWang/img/cancelfullscreen.png
MavenRumenjiaochengCYuyanBianchengWang/img/close.png
MavenRumenjiaochengCYuyanBianchengWang/img/fullscreen.png
MavenRumenjiaochengCYuyanBianchengWang/img/loader.gif
MavenRumenjiaochengCYuyanBianchengWang/img/menu-icon.png
MavenRumenjiaochengCYuyanBianchengWang/img/save.png
MavenRumenjiaochengCYuyanBianchengWang/img/saved.png
MavenRumenjiaochengCYuyanBianchengWang/img/settings-s.png
MavenRumenjiaochengCYuyanBianchengWang/img/settings.png
MavenRumenjiaochengCYuyanBianchengWang/img/star.png
MavenRumenjiaochengCYuyanBianchengWang/js/__init__.py
MavenRumenjiaochengCYuyanBianchengWang/js/epub.js
MavenRumenjiaochengCYuyanBianchengWang/js/epub.min.js
MavenRumenjiaochengCYuyanBianchengWang/js/epub.min.map
MavenRumenjiaochengCYuyanBianchengWang/js/hooks.min.js
MavenRumenjiaochengCYuyanBianchengWang/js/hooks.min.map
maven_rumenjiaocheng_c_yuyan_biancheng_wang-2024.3.5.0.dist-info/METADATA
maven_rumenjiaocheng_c_yuyan_biancheng_wang-2024.3.5.0.dist-info/WHEEL
maven_rumenjiaocheng_c_yuyan_biancheng_wang-2024.3.5.0.dist-info/entry_points.txt
maven_rumenjiaocheng_c_yuyan_biancheng_wang-2024.3.5.0.dist-info/top_level.txt
maven_rumenjiaocheng_c_yuyan_biancheng_wang-2024.3.5.0.dist-info/RECORD
